slai_cli/__init__.py
slai_cli/__main__.py
slai_cli/cli.py
slai_cli/constants.py
slai_cli/decorators.py
slai_cli/errors.py
slai_cli/exceptions.py
slai_cli/log.py
slai_cli/main.py
slai_cli/model/__init__.py
slai_cli/model/call.py
slai_cli/model/checkout.py
slai_cli/model/commands.py
slai_cli/model/create.py
slai_cli/model/deploy.py
slai_cli/model/list.py
slai_cli/model/open.py
slai_cli/model/save.py
slai_cli/model/templates/handler.py
slai_cli/model/templates/model.yml
slai_cli/model/templates/notebook.ipynb
slai_cli/model/templates/test_event.json
slai_cli/model/test.py
slai_cli/model/train.py
slai_cli/modules/__init__.py
slai_cli/modules/bundle_model.py
slai_cli/modules/deployment_checks.py
slai_cli/modules/docker_client.py
slai_cli/modules/drive_client.py
slai_cli/modules/model_watcher.py
slai_cli/modules/stoppable_thread.py
slai_cli/profile/__init__.py
slai_cli/profile/commands.py
slai_cli/profile/configure.py
slai_cli/profile/list.py
slai_cli/syncer.py
slai_cli-0.7.7.dist-info/entry_points.txt
slai_cli-0.7.7.dist-info/WHEEL
slai_cli-0.7.7.dist-info/METADATA
slai_cli-0.7.7.dist-info/RECORD
