Metadata-Version: 2.1
Name: slai-cli
Version: 0.7.7
Summary: 
Author: slai
Author-email: luke@slai.io
Requires-Python: >=3.7.1,<4.0.0
Classifier: Programming Language :: Python :: 3
Classifier: Programming Language :: Python :: 3.8
Classifier: Programming Language :: Python :: 3.9
Requires-Dist: Columnar (>=1.3.1,<2.0.0)
Requires-Dist: Flask (>=1.1.2,<2.0.0)
Requires-Dist: Flask-Cors (>=3.0.9,<4.0.0)
Requires-Dist: GitPython (>=3.1.11,<4.0.0)
Requires-Dist: Jinja2 (>=2.11.2,<3.0.0)
Requires-Dist: PyDrive (>=1.3.1,<2.0.0)
Requires-Dist: PyYAML (>=6.0,<7.0)
Requires-Dist: boto3 (>=1.16.44,<2.0.0)
Requires-Dist: celery (==5.0.2)
Requires-Dist: click (>=7.1.2,<8.0.0)
Requires-Dist: dill (>=0.3.3,<0.4.0)
Requires-Dist: docker (>=5.0.0,<6.0.0)
Requires-Dist: python-dotenv (>=0.15.0,<0.16.0)
Requires-Dist: redis (>=3.5.3,<4.0.0)
Requires-Dist: shtab (>=1.3.4,<2.0.0)
Requires-Dist: slai (==0.1.76)
